usl_embedding/__init__.py
usl_embedding/selective_labeling.py
usl_embedding/methods/__init__.py
usl_embedding/methods/usl.py
usl_embedding/methods/usl_t.py
usl_embedding/models/__init__.py
usl_embedding/models/ssl_t_models/__init__.py
usl_embedding/models/ssl_t_models/clustering_model.py
usl_embedding-0.1.2.dist-info/LICENSE
usl_embedding-0.1.2.dist-info/METADATA
usl_embedding-0.1.2.dist-info/WHEEL
usl_embedding-0.1.2.dist-info/entry_points.txt
usl_embedding-0.1.2.dist-info/top_level.txt
usl_embedding-0.1.2.dist-info/RECORD
