Metadata-Version: 2.1
Name: usl_embedding
Version: 0.1.2
Summary: Implements the USL Technique for embeddings of any data, be it text, image, etc.
Home-page: https://github.com/Hosseini1373/usl_for_embedding
Author: Ahmad Hosseini, ZHAW
Author-email: s.ahmad.hosseini94@gmail.com
Classifier: Programming Language :: Python :: 3
Classifier: License :: OSI Approved :: MIT License
Classifier: Operating System :: OS Independent
Requires-Python: >=3.6
License-File: LICENSE
Requires-Dist: numpy
Requires-Dist: pandas
Requires-Dist: scikit-learn
Requires-Dist: torch
